{
    "nodes": [
      {
        "NODE_HOME": "/data/node/validator0/",
        "MONIKER": "node0",
        "CHAIN_ID": "treasurenet_5005-1",
        "KEYRING": "file",
        "KEY1": "validator0",
        "KEY2": "orchestrator0",
        "ALLOCATION": "10000000000000000000000aunit,10000000000stake,10000000000ibc/token",
        "BIN": "treasurenetd",
        "KEYALGO": "eth_secp256k1",
        "LOGLEVEL": "info"
      },
      {
        "NODE_HOME": "/data/node/validator1/",
        "MONIKER": "node1",
        "CHAIN_ID": "treasurenet_5005-1",
        "KEYRING": "file",
        "KEY1": "validator1",
        "KEY2": "orchestrator1",
        "ALLOCATION": "10000000000000000000000aunit,10000000000stake,10000000000ibc/token",
        "BIN": "treasurenetd",
        "KEYALGO": "eth_secp256k1",
        "LOGLEVEL": "info"
      },
      {
        "NODE_HOME": "/data/node/validator2/",
        "MONIKER": "node2",
        "CHAIN_ID": "treasurenet_5005-1",
        "KEYRING": "file",
        "KEY1": "validator2",
        "KEY2": "orchestrator2",
        "ALLOCATION": "10000000000000000000000aunit,10000000000stake,10000000000ibc/token",
        "BIN": "treasurenetd",
        "KEYALGO": "eth_secp256k1",
        "LOGLEVEL": "info"
      },
      {
        "NODE_HOME": "/data/node/validator3/",
        "MONIKER": "node3",
        "CHAIN_ID": "treasurenet_5005-1",
        "KEYRING": "file",
        "KEY1": "validator3",
        "KEY2": "orchestrator3",
        "ALLOCATION": "10000000000000000000000aunit,10000000000stake,10000000000ibc/token",
        "BIN": "treasurenetd",
        "KEYALGO": "eth_secp256k1",
        "LOGLEVEL": "info"
      }
    ]
  }
  